jemma/config.py
jemma/init.py
jemma/main.py
jemma/model/commandWatch.py
jemma/model/editCode.py
jemma/model/explainCodebase.py
jemma/model/modelInteraction.py
jemma/model/startSession.py
jemma/utils/fileSpitter.py
jemma/utils/getApiKey.py
jemma/utils/getConfig.py
jemma/utils/getFilesContent.py
jemma/utils/replaceFileContentByLines.py
jemma/utils/terminalPrettifier.py
jemma_code-0.1.1.dist-info/licenses/LICENSE
jemma_code-0.1.1.dist-info/METADATA
jemma_code-0.1.1.dist-info/WHEEL
jemma_code-0.1.1.dist-info/entry_points.txt
jemma_code-0.1.1.dist-info/top_level.txt
jemma_code-0.1.1.dist-info/RECORD
