Metadata-Version: 2.4
Name: jemma-code
Version: 0.1.1
Summary: Get coding help, right in your terminal
Author-email: Alabi Ayobami <arocket04@gmail.com>
Keywords: code,code assistant,gemini,api
Classifier: Development Status :: 3 - Alpha
Classifier: Intended Audience :: Developers
Classifier: Programming Language :: Python :: 3
Classifier: Programming Language :: Python :: 3.6
Classifier: Programming Language :: Python :: 3.7
Classifier: Programming Language :: Python :: 3.8
Classifier: Programming Language :: Python :: 3.9
Requires-Python: >=3.6
License-File: LICENSE
Requires-Dist: requests>=2.25.0
Requires-Dist: colorama
Dynamic: license-file
